[
	{
		"fiatCurrency": "AUD",
		"coinValues": [0.05, 0.1, 0.2, 0.5, 1, 2],
		"coinValueIncrement": 0.05,
		"billValues": [5, 10, 20, 50, 100],
		"fiatPrecision": 2,
		"buyLimit": 400
	},
	{
		"fiatCurrency": "BAM",
		"coinValues": [0.1, 0.2, 0.5, 1, 2, 5],
		"coinValueIncrement": 0.1,
		"billValues": [10, 20, 50, 100, 200],
		"fiatPrecision": 2,
		"buyLimit": 500
	},
	{
		"fiatCurrency": "BGN",
		"coinValues": [0.05, 0.1, 0.25, 0.5, 1],
		"coinValueIncrement": 0.05,
		"billValues": [2, 5, 10, 20, 50, 100],
		"fiatPrecision": 2,
		"buyLimit": 500
	},
	{
		"fiatCurrency": "BRL",
		"coinValues": [0.05, 0.1, 0.25, 0.5, 1],
		"coinValueIncrement": 0.05,
		"billValues": [2, 5, 10, 20, 50, 100, 200],
		"fiatPrecision": 2,
		"buyLimit": 1300
	},
	{
		"fiatCurrency": "CAD",
		"coinValues": [0.05, 0.1, 0.25, 0.5, 1],
		"coinValueIncrement": 0.05,
		"billValues": [5, 10, 20, 50, 100],
		"fiatPrecision": 2,
		"buyLimit": 350
	},
	{
		"fiatCurrency": "CHF",
		"coinValues": [0.1, 0.2, 0.5, 1, 2, 5],
		"coinValueIncrement": 0.1,
		"billValues": [10, 20, 50, 100, 200],
		"fiatPrecision": 2,
		"buyLimit": 500
	},
	{
		"fiatCurrency": "CLP",
		"coinValues": [50, 100, 500],
		"coinValueIncrement": 50,
		"billValues": [1000, 2000, 5000, 10000, 20000],
		"fiatPrecision": 0,
		"buyLimit": 250000
	},
	{
		"fiatCurrency": "COP",
		"coinValues": [50, 100, 500, 1000],
		"coinValueIncrement": 50,
		"billValues": [1000, 2000, 5000, 10000, 20000, 50000, 100000],
		"fiatPrecision": 0,
		"buyLimit": 1000000
	},
	{
		"fiatCurrency": "CRC",
		"coinValues": [10, 25, 50, 100, 500],
		"coinValueIncrement": 5,
		"billValues": [1000, 2000, 5000, 10000, 20000],
		"fiatPrecision": 0,
		"buyLimit": 120000
	},
	{
		"fiatCurrency": "CZK",
		"coinValues": [1, 2, 5, 10, 20, 50],
		"coinValueIncrement": 1,
		"billValues": [100, 200, 500, 1000, 2000],
		"fiatPrecision": 0,
		"buyLimit": 6000
	},
	{
		"fiatCurrency": "DKK",
		"coinValues": [0.5, 1, 2, 5, 10, 20],
		"coinValueIncrement": 0.5,
		"billValues": [50, 100, 200, 500, 1000],
		"fiatPrecision": 2,
		"buyLimit": 2000
	},
	{
		"fiatCurrency": "EUR",
		"coinValues": [0.05, 0.1, 0.2, 0.5, 1, 2],
		"coinValueIncrement": 0.05,
		"billValues": [5, 10, 20, 50, 100, 200],
		"fiatPrecision": 2,
		"buyLimit": 250
	},
	{
		"fiatCurrency": "GBP",
		"coinValues": [0.1, 0.2, 0.5, 1, 2, 5],
		"coinValueIncrement": 0.1,
		"billValues": [5, 10, 20, 50],
		"fiatPrecision": 2,
		"buyLimit": 250
	},
	{
		"fiatCurrency": "GHS",
		"coinValues": [0.05, 0.1, 0.2, 0.5, 1, 2],
		"coinValueIncrement": 0.05,
		"billValues": [2, 5, 10, 20, 50, 100],
		"fiatPrecision": 2,
		"buyLimit": 2000
	},
	{
		"fiatCurrency": "HKD",
		"coinValues": [0.1, 0.2, 0.5, 1, 2, 5],
		"coinValueIncrement": 0.1,
		"billValues": [10, 20, 50, 100, 500, 1000],
		"fiatPrecision": 2,
		"buyLimit": 2000
	},
	{
		"fiatCurrency": "HRK",
		"coinValues": [0.1, 0.2, 0.5, 1, 2, 5],
		"coinValueIncrement": 0.1,
		"billValues": [10, 20, 50, 100, 200, 500, 1000],
		"fiatPrecision": 2,
		"buyLimit": 2000
	},
	{
		"fiatCurrency": "HUF",
		"coinValues": [5, 10, 20, 50, 100, 200],
		"coinValueIncrement": 5,
		"billValues": [500, 1000, 2000, 5000, 10000, 20000],
		"fiatPrecision": 0,
		"buyLimit": 100000
	},
	{
		"fiatCurrency": "IDR",
		"coinValues": [500, 1000],
		"coinValueIncrement": 500,
		"billValues": [1000, 2000, 5000, 10000, 20000, 50000],
		"fiatPrecision": 0,
		"buyLimit": 100000
	},
	{
		"fiatCurrency": "INR",
		"coinValues": [1, 2, 5, 10],
		"coinValueIncrement": 1,
		"billValues": [10, 20, 50, 100, 200, 500],
		"fiatPrecision": 0,
		"buyLimit": 15000
	},
	{
		"fiatCurrency": "ISK",
		"coinValues": [5, 10, 50, 100],
		"coinValueIncrement": 5,
		"billValues": [500, 1000, 2000, 5000, 10000],
		"fiatPrecision": 0,
		"buyLimit": 40000
	},
	{
		"fiatCurrency": "JMD",
		"coinValues": [5, 10, 20],
		"coinValueIncrement": 5,
		"billValues": [50, 100, 500, 1000, 2000],
		"fiatPrecision": 0,
		"buyLimit": 30000
	},
	{
		"fiatCurrency": "JPY",
		"coinValues": [5, 10, 50, 100, 500],
		"coinValueIncrement": 5,
		"billValues": [1000, 5000, 10000],
		"fiatPrecision": 0,
		"buyLimit": 50000
	},
	{
		"fiatCurrency": "KRW",
		"coinValues": [10, 50, 100, 500],
		"coinValueIncrement": 10,
		"billValues": [1000, 5000, 10000, 50000],
		"fiatPrecision": 0,
		"buyLimit": 400000
	},
	{
		"fiatCurrency": "MAD",
		"coinValues": [0.2, 0.5, 1, 2, 5, 10],
		"coinValueIncrement": 0.1,
		"billValues": [20, 50, 100, 200],
		"fiatPrecision": 2,
		"buyLimit": 2000
	},
	{
		"fiatCurrency": "MKD",
		"coinValues": [1, 2, 5, 10, 50],
		"coinValueIncrement": 1,
		"billValues": [50, 100, 200, 500, 1000, 2000],
		"fiatPrecision": 0,
		"buyLimit": 16000
	},
	{
		"fiatCurrency": "MXN",
		"coinValues": [0.5, 1, 2, 5, 10],
		"coinValueIncrement": 0.5,
		"billValues": [20, 50, 100, 200, 500],
		"fiatPrecision": 2,
		"buyLimit": 5000
	},
	{
		"fiatCurrency": "NGN",
		"coinValues": [0.5, 1, 2],
		"coinValueIncrement": 0.5,
		"billValues": [20, 50, 100, 200, 500, 1000],
		"fiatPrecision": 2,
		"buyLimit": 150000
	},
	{
		"fiatCurrency": "NOK",
		"coinValues": [1, 5, 10, 20],
		"coinValueIncrement": 1,
		"billValues": [50, 100, 200, 500, 1000],
		"fiatPrecision": 0,
		"buyLimit": 2500
	},
	{
		"fiatCurrency": "NZD",
		"coinValues": [0.1, 0.2, 0.5, 1, 2],
		"coinValueIncrement": 0.1,
		"billValues": [5, 10, 20, 50, 100],
		"fiatPrecision": 2,
		"buyLimit": 450
	},
	{
		"fiatCurrency": "PEN",
		"coinValues": [0.1, 0.2, 0.5, 1, 2, 5],
		"coinValueIncrement": 0.1,
		"billValues": [10, 20, 50, 100, 200],
		"fiatPrecision": 2,
		"buyLimit": 1000
	},
	{
		"fiatCurrency": "PHP",
		"coinValues": [1, 5, 10, 20],
		"coinValueIncrement": 1,
		"billValues": [20, 50, 100, 500, 1000],
		"fiatPrecision": 0,
		"buyLimit": 12000
	},
	{
		"fiatCurrency": "PLN",
		"coinValues": [0.1, 0.2, 0.5, 1, 2, 5],
		"coinValueIncrement": 0.1,
		"billValues": [10, 20, 50, 100, 200, 500],
		"fiatPrecision": 2,
		"buyLimit": 1000
	},
	{
		"fiatCurrency": "PYG",
		"coinValues": [50, 100, 500, 1000],
		"coinValueIncrement": 50,
		"billValues": [2000, 5000, 10000, 20000, 50000, 100000],
		"fiatPrecision": 0,
		"buyLimit": 1500000
	},
	{
		"fiatCurrency": "RON",
		"coinValues": [0.05, 0.1, 0.5],
		"coinValueIncrement": 0.05,
		"billValues": [1, 5, 10, 50, 100, 200, 500],
		"fiatPrecision": 2,
		"buyLimit": 1250
	},
	{
		"fiatCurrency": "SEK",
		"coinValues": [1, 2, 5, 10],
		"coinValueIncrement": 1,
		"billValues": [20, 50, 100, 200, 500],
		"fiatPrecision": 0,
		"buyLimit": 2500
	},
	{
		"fiatCurrency": "SGD",
		"coinValues": [0.05, 0.1, 0.2, 0.5, 1],
		"coinValueIncrement": 0.05,
		"billValues": [2, 5, 10, 50, 100],
		"fiatPrecision": 2,
		"buyLimit": 400
	},
	{
		"fiatCurrency": "THB",
		"coinValues": [0.25, 0.5, 1, 2, 5, 10],
		"coinValueIncrement": 0.25,
		"billValues": [20, 50, 100, 500, 1000],
		"fiatPrecision": 2,
		"buyLimit": 10000
	},
	{
		"fiatCurrency": "TRY",
		"coinValues": [0.05, 0.1, 0.25, 0.5, 1],
		"coinValueIncrement": 0.05,
		"billValues": [5, 10, 20, 50, 100, 200],
		"fiatPrecision": 2,
		"buyLimit": 4000
	},
	{
		"fiatCurrency": "UGX",
		"coinValues": [100, 200, 500, 1000],
		"coinValueIncrement": 100,
		"billValues": [1000, 2000, 5000, 10000, 20000, 50000],
		"fiatPrecision": 0,
		"buyLimit": 1000000
	},
	{
		"fiatCurrency": "USD",
		"coinValues": [0.05, 0.1, 0.25, 0.5, 1],
		"coinValueIncrement": 0.05,
		"billValues": [1, 5, 10, 20, 50, 100],
		"fiatPrecision": 2,
		"buyLimit": 250
	},
	{
		"fiatCurrency": "VND",
		"coinValues": [],
		"coinValueIncrement": 1,
		"billValues": [5000, 10000, 20000, 50000, 100000, 200000],
		"fiatPrecision": 0,
		"buyLimit": 2000000
	},
	{
		"fiatCurrency": "ZAR",
		"coinValues": [0.1, 0.2, 0.5, 1, 2, 5],
		"coinValueIncrement": 0.1,
		"billValues": [10, 20, 50, 100, 200],
		"fiatPrecision": 2,
		"buyLimit": 3000
	}
]